[
    {
        "id": "0000b31a",
        "charaName": "Saito Tsutomu"
    },
    {
        "id": "0000b31e",
        "charaName": "Yuichi Hongo"
    },
    {
        "id": "0000b320",
        "charaName": "Akira Onuki"
    },
    {
        "id": "0000b32a",
        "charaName": "Was it just like that"
    },
    {
        "id": "0000b333",
        "charaName": "Honda Haraumi"
    },
    {
        "id": "0000b335",
        "charaName": "Other"
    },
    {
        "id": "0000b375",
        "charaName": "As expected"
    },
    {
        "id": "0000b3cf",
        "charaName": "As expected"
    },
    {
        "id": "0000b3f5",
        "charaName": "As expected"
    },
    {
        "id": "0000b4ab",
        "charaName": "As expected"
    },
    {
        "id": "0000b598",
        "charaName": "Keiko Mizukoshi"
    },
    {
        "id": "0000b8d7",
        "charaName": "Bully A"
    },
    {
        "id": "0000b938",
        "charaName": "Bully A brother"
    },
    {
        "id": "0000c2a7",
        "charaName": "Asagaka"
    },
    {
        "id": "0000c6ba",
        "charaName": "Mr. Principal"
    },
    {
        "id": "0000ce12",
        "charaName": "Honda Hara"
    }
]