[
    {
        "id": "00010066",
        "charaName": "Tetsuro Murakami"
    },
    {
        "id": "00010068",
        "charaName": "Daitokuji Hineko"
    },
    {
        "id": "00010074",
        "charaName": "Dean"
    },
    {
        "id": "00010080",
        "charaName": "Field \u53b3\u8535"
    },
    {
        "id": "000100ab",
        "charaName": "Kisaragi Yui"
    },
    {
        "id": "000100d4",
        "charaName": "Ryo Sakurai"
    },
    {
        "id": "00010500",
        "charaName": "Sakurai Erina"
    },
    {
        "id": "00010a73",
        "charaName": "Kyoko Asukagawa"
    }
]